LICENSE
MANIFEST.in
README
akara
setup.py
Akara.egg-info/SOURCES.txt
akara.egg-info/PKG-INFO
akara.egg-info/SOURCES.txt
akara.egg-info/dependency_links.txt
akara.egg-info/not-zip-safe
akara.egg-info/top_level.txt
demo/modules/README
demo/modules/akara_tests.py
demo/modules/atompub.py
demo/modules/atomtools.py
demo/modules/calaistools.py
demo/modules/calweb.py
demo/modules/collection.py
demo/modules/discovery.py
demo/modules/echo.py
demo/modules/exhibittools.py
demo/modules/icaltools.py
demo/modules/luckygoogle.py
demo/modules/markuptools.py
demo/modules/method_dispatcher.py
demo/modules/moin2atomentries.py
demo/modules/moincms.py
demo/modules/moinrest.py
demo/modules/oaitools.py
demo/modules/rdfatools.py
demo/modules/static.py
demo/modules/statstools.py
demo/modules/svntools.py
demo/modules/unicodetools.py
demo/modules/wwwlogviewer.py
demo/modules/xslt.py
lib/__init__.py
lib/caching.py
lib/commandline.py
lib/dist.py
lib/global_config.py
lib/logger_config.py
lib/multiprocess_http.py
lib/pipeline.py
lib/read_config.py
lib/registry.py
lib/request.py
lib/response.py
lib/run.py
lib/services.py
lib/resource/__init__.py
lib/resource/index.py
lib/resource/web.py
lib/resource/repository/__init__.py
lib/restwrap/__init__.py
lib/restwrap/moin.py
lib/thirdparty/__init__.py
lib/thirdparty/argparse.py
lib/thirdparty/httpserver.py
lib/thirdparty/preforkserver.py
lib/transform/__init__.py
lib/transform/middleware.py
lib/transform/xslt.py
lib/util/__init__.py
lib/util/moin.py
lib/util/multipart_post_handler.py
test/README
test/python_support.py
test/python_support.pyc
test/server_support.py
test/server_support.pyc
test/test_commandline.py
test/test_commandline.pyc
test/test_demo_modules.py
test/test_demo_modules.pyc
test/test_internals.py
test/test_internals.pyc
test/test_pipeline.py
test/test_server.py
test/test_server.pyc
test/test_services.py
test/test_services.pyc
test/test_setup_py.py
test/resource/icalendar_test.ics
test/resource/widefinder_100.apache_log
test/resource/xslt_spec_example.xml
test/resource/xslt_spec_example.xslt
test/resource/atom/entry1.atom
test/resource/atom/entry2.atom
test/resource/atom/entry3.atom
