Metadata-Version: 1.0
Name: Akara
Version: 2.0a1
Summary: Web components for Amara 2.x
Home-page: http://wiki.xml3k.org/Akara
Author: Uche Ogbuji and others
Author-email: amara-dev@googlegroups.com
License: UNKNOWN
Platform: UNKNOWN
